adif_parser/__init__.py
adif_parser/py.typed
adif_parser-0.1.7.dist-info/licenses/LICENSE
adif_parser-0.1.7.dist-info/METADATA
adif_parser-0.1.7.dist-info/WHEEL
adif_parser-0.1.7.dist-info/top_level.txt
adif_parser-0.1.7.dist-info/RECORD
