Metadata-Version: 2.4
Name: adif_parser
Version: 0.1.7
Summary: A simple parser library.
Author-email: Fred cC <w6bsd@bsdworld.org>
License: BSD 2-Clause License
Project-URL: Homepage, https://github.com/0x9900/adif_parser
Project-URL: Documentation, https://github.com/0x9900/adif_parser/
Project-URL: Source, https://github.com/0x9900/adif_parser
Project-URL: Tracker, https://github.com/0x9900/adif_parser/issues
Classifier: Intended Audience :: End Users/Desktop
Classifier: Intended Audience :: Telecommunications Industry
Classifier: License :: OSI Approved :: BSD License
Classifier: Operating System :: MacOS
Classifier: Operating System :: POSIX :: Linux
Classifier: Programming Language :: Python
Classifier: Programming Language :: Python :: 3.10
Requires-Python: >=3.10
License-File: LICENSE
Provides-Extra: dev
Requires-Dist: build; extra == "dev"
Requires-Dist: flake8; extra == "dev"
Requires-Dist: ipdb; extra == "dev"
Requires-Dist: ipython; extra == "dev"
Requires-Dist: isort; extra == "dev"
Requires-Dist: mypy; extra == "dev"
Requires-Dist: pre-commit; extra == "dev"
Requires-Dist: pylint; extra == "dev"
Dynamic: license-file
